dvadmin_request_intercept/__init__.py
dvadmin_request_intercept/apps.py
dvadmin_request_intercept/middleware.py
dvadmin_request_intercept-1.0.0.dist-info/LICENSE
dvadmin_request_intercept-1.0.0.dist-info/METADATA
dvadmin_request_intercept-1.0.0.dist-info/WHEEL
dvadmin_request_intercept-1.0.0.dist-info/top_level.txt
dvadmin_request_intercept-1.0.0.dist-info/RECORD
