Metadata-Version: 2.1
Name: dvadmin-request-intercept
Version: 1.0.0
Summary: dvadmin用来全局拦截指定请求方式及请求插件
Home-page: https://gitee.com/huge-dream/dvadmin-request-intercept
Author: DVAdmin
Author-email: liqiang@django-vue-admin.com
License: UNKNOWN
Platform: UNKNOWN
Classifier: Programming Language :: Python :: 3
Classifier: License :: OSI Approved :: MIT License
Classifier: Operating System :: OS Independent
Requires-Python: >=3.6, <4
License-File: LICENSE
